tree_sitter_mal/__init__.pyi
tree_sitter_mal/binding.c
tree_sitter_mal/__init__.py
tree_sitter_mal/py.typed
tree_sitter_mal/_binding.abi3.so
tree_sitter_mal/queries/highlights.scm
tree_sitter_mal-1.0.2.dist-info/RECORD
tree_sitter_mal-1.0.2.dist-info/WHEEL
tree_sitter_mal-1.0.2.dist-info/top_level.txt
tree_sitter_mal-1.0.2.dist-info/METADATA
