Metadata-Version: 2.4
Name: tree-sitter-mal
Version: 1.0.2
Summary: IT systems are growing in complexity and the threat from cyberattacks is increasing. Threat modeling is a process that can be used to analyze potential attacks to IT systems in order to facilitate secure design. Meta Attack Language (MAL) is a threat modeling language framework for the creation of domain specific languages (DSL). MAL is developed at KTH Royal Institute of Technology.
Author-email: Andreas Hammarstrand <andreas.hammarstrand@gmail.com>
License: MIT
Project-URL: Homepage, https://github.com/tobiky/tree-sitter-mal
Keywords: incremental,parsing,tree-sitter,mal
Classifier: Intended Audience :: Developers
Classifier: Topic :: Software Development :: Compilers
Classifier: Topic :: Text Processing :: Linguistic
Classifier: Typing :: Typed
Requires-Python: >=3.9
Provides-Extra: core
Requires-Dist: tree-sitter~=0.22; extra == "core"
